kle2netlist/__init__.py
kle2netlist/__main__.py
kle2netlist/_version.py
kle2netlist/skidl.py
kle2netlist/data/kicad-symbols/.git
kle2netlist/data/kicad-symbols/.gitattributes
kle2netlist/data/kicad-symbols/.gitignore
kle2netlist/data/kicad-symbols/.gitlab-ci.yml
kle2netlist/data/kicad-symbols/4xxx.kicad_sym
kle2netlist/data/kicad-symbols/4xxx_IEEE.kicad_sym
kle2netlist/data/kicad-symbols/74xGxx.kicad_sym
kle2netlist/data/kicad-symbols/74xx.kicad_sym
kle2netlist/data/kicad-symbols/74xx_IEEE.kicad_sym
kle2netlist/data/kicad-symbols/Amplifier_Audio.kicad_sym
kle2netlist/data/kicad-symbols/Amplifier_Buffer.kicad_sym
kle2netlist/data/kicad-symbols/Amplifier_Current.kicad_sym
kle2netlist/data/kicad-symbols/Amplifier_Difference.kicad_sym
kle2netlist/data/kicad-symbols/Amplifier_Instrumentation.kicad_sym
kle2netlist/data/kicad-symbols/Amplifier_Operational.kicad_sym
kle2netlist/data/kicad-symbols/Amplifier_Video.kicad_sym
kle2netlist/data/kicad-symbols/Analog.kicad_sym
kle2netlist/data/kicad-symbols/Analog_ADC.kicad_sym
kle2netlist/data/kicad-symbols/Analog_DAC.kicad_sym
kle2netlist/data/kicad-symbols/Analog_Switch.kicad_sym
kle2netlist/data/kicad-symbols/Audio.kicad_sym
kle2netlist/data/kicad-symbols/Battery_Management.kicad_sym
kle2netlist/data/kicad-symbols/Buffer.kicad_sym
kle2netlist/data/kicad-symbols/CMakeLists.txt
kle2netlist/data/kicad-symbols/CONTRIBUTING.md
kle2netlist/data/kicad-symbols/CPLD_Altera.kicad_sym
kle2netlist/data/kicad-symbols/CPLD_Microchip.kicad_sym
kle2netlist/data/kicad-symbols/CPLD_Xilinx.kicad_sym
kle2netlist/data/kicad-symbols/CPU.kicad_sym
kle2netlist/data/kicad-symbols/CPU_NXP_6800.kicad_sym
kle2netlist/data/kicad-symbols/CPU_NXP_68000.kicad_sym
kle2netlist/data/kicad-symbols/CPU_NXP_IMX.kicad_sym
kle2netlist/data/kicad-symbols/CPU_PowerPC.kicad_sym
kle2netlist/data/kicad-symbols/Comparator.kicad_sym
kle2netlist/data/kicad-symbols/Connector.kicad_sym
kle2netlist/data/kicad-symbols/Connector_Audio.kicad_sym
kle2netlist-0.4.0.dist-info/METADATA
kle2netlist-0.4.0.dist-info/WHEEL
kle2netlist-0.4.0.dist-info/entry_points.txt
kle2netlist-0.4.0.dist-info/licenses/LICENSE
kle2netlist-0.4.0.dist-info/RECORD
