Metadata-Version: 2.1
Name: kle2netlist
Version: 0.4.0
Summary: KiCad netlist generator for mechanical keyboards 
Project-URL: Documentation, https://github.com/adamws/kle2netlist#readme
Project-URL: Issues, https://github.com/adamws/kle2netlist/issues
Project-URL: Source, https://github.com/adamws/kle2netlist
Author-email: adamws <adamws@users.noreply.github.com>
License-Expression: MIT
License-File: LICENSE
Classifier: Development Status :: 3 - Alpha
Classifier: Intended Audience :: Developers
Classifier: Operating System :: OS Independent
Classifier: Topic :: Software Development :: Libraries :: Python Modules
Requires-Python: >=3.7
Requires-Dist: rich
Requires-Dist: skidl===1.0.0
Requires-Dist: typer[all]>=0.9
